ligo/__init__.py
ligo/IO/__init__.py
ligo/IO/dataset_export/AIRRExporter.py
ligo/IO/dataset_export/DataExporter.py
ligo/IO/dataset_export/ImmuneMLExporter.py
ligo/IO/dataset_export/__init__.py
ligo/IO/dataset_import/AIRRImport.py
ligo/IO/dataset_import/DataImport.py
ligo/IO/dataset_import/DatasetImportParams.py
ligo/IO/dataset_import/GenericImport.py
ligo/IO/dataset_import/IGoRImport.py
ligo/IO/dataset_import/IReceptorImport.py
ligo/IO/dataset_import/ImmuneMLImport.py
ligo/IO/dataset_import/ImmunoSEQRearrangementImport.py
ligo/IO/dataset_import/ImmunoSEQSampleImport.py
ligo/IO/dataset_import/MiXCRImport.py
ligo/IO/dataset_import/OLGAImport.py
ligo/IO/dataset_import/SingleLineReceptorImport.py
ligo/IO/dataset_import/TenxGenomicsImport.py
ligo/IO/dataset_import/VDJdbImport.py
ligo/IO/dataset_import/__init__.py
ligo/IO/dataset_import/conversion/imgt_adaptive_conversion.csv
ligo/app/LigoApp.py
ligo/app/__init__.py
ligo/config/default_params/datasets/airr_params.yaml
ligo/config/default_params/datasets/generic_params.yaml
ligo/config/default_params/datasets/i_receptor_params.yaml
ligo/config/default_params/datasets/igor_params.yaml
ligo/config/default_params/datasets/immuno_seq_rearrangement_params.yaml
ligo/config/default_params/datasets/immuno_seq_sample_params.yaml
ligo/config/default_params/datasets/mixcr_params.yaml
ligo/config/default_params/datasets/olga_params.yaml
ligo/config/default_params/datasets/random_receptor_dataset_params.yaml
ligo/config/default_params/datasets/random_repertoire_dataset_params.yaml
ligo/config/default_params/datasets/random_sequence_dataset_params.yaml
ligo/config/default_params/datasets/tenx_genomics_params.yaml
ligo/config/default_params/datasets/vdjdb_params.yaml
ligo/config/default_params/instructions/feasibility_summary_params.yaml
ligo/config/default_params/instructions/ligo_sim_params.yaml
ligo/config/default_params/simulation/ligo_sim_config_item_params.yaml
ligo/config/default_params/simulation/ligo_sim_config_params.yaml
ligo-1.0.11.dist-info/licenses/LICENSE.md
ligo-1.0.11.dist-info/METADATA
ligo-1.0.11.dist-info/WHEEL
ligo-1.0.11.dist-info/entry_points.txt
ligo-1.0.11.dist-info/top_level.txt
ligo-1.0.11.dist-info/RECORD
