Metadata-Version: 2.4
Name: ligo
Version: 1.0.11
Summary: LIgO is a tool for simulation of adaptive immune receptors and repertoires.
Home-page: https://github.com/uio-bmi/ligo
Author: Milena Pavlovic
Author-email: milenpa@student.matnat.uio.no
Classifier: Programming Language :: Python :: 3
Classifier: License :: OSI Approved :: GNU Affero General Public License v3
Requires-Python: >=3.11
License-File: LICENSE.md
Requires-Dist: pandas
Requires-Dist: bionumpy>=0.2.26
Requires-Dist: olga
Requires-Dist: pyyaml
Requires-Dist: airr
Requires-Dist: plotly
Requires-Dist: pystache
Requires-Dist: scipy
Requires-Dist: stitchr
Requires-Dist: IMGTgeneDL
Requires-Dist: dill
Requires-Dist: numpy
Dynamic: author
Dynamic: author-email
Dynamic: classifier
Dynamic: description
Dynamic: description-content-type
Dynamic: home-page
Dynamic: license-file
Dynamic: requires-dist
Dynamic: requires-python
Dynamic: summary
